nlbq/__init__.py
nlbq/api.py
nlbq/cli.py
nlbq/config.py
nlbq/core.py
nlbq/helpers.py
nlbq/templates/Dockerfile
nlbq/templates/index.html
nlbq/templates/prompt.txt
nlbq/templates/prompt_template.txt
nlbq-0.1.7.dist-info/entry_points.txt
nlbq-0.1.7.dist-info/LICENSE
nlbq-0.1.7.dist-info/WHEEL
nlbq-0.1.7.dist-info/METADATA
nlbq-0.1.7.dist-info/RECORD
