Metadata-Version: 2.1
Name: nlbq
Version: 0.1.7
Summary: Natural language to BigQuery
Author: Tom Dyson, Dan Braghis
Requires-Python: >=3.11
Classifier: License :: OSI Approved :: MIT License
Requires-Dist: openai
Requires-Dist: fastapi
Requires-Dist: pydantic-settings
Requires-Dist: uvicorn[standard]
Requires-Dist: tabulate
Requires-Dist: typer
Requires-Dist: python-dotenv
Requires-Dist: nldb
Requires-Dist: google-cloud-bigquery
Requires-Dist: pre-commit >=3.3.2 ; extra == "lint"
Project-URL: Home, https://github.com/torchbox/nlbq
Provides-Extra: lint
